mooquant_bitfinex/__init__.py
mooquant_bitfinex/api.py
mooquant_bitfinex/broker.py
mooquant_bitfinex/common.py
mooquant_bitfinex/livefeed.py
mooquant_bitfinex-0.1.2.dist-info/METADATA
mooquant_bitfinex-0.1.2.dist-info/RECORD
mooquant_bitfinex-0.1.2.dist-info/WHEEL
mooquant_bitfinex-0.1.2.dist-info/top_level.txt
