Metadata-Version: 2.1
Name: mooquant-bitfinex
Version: 0.1.2
Summary: mooquant bitfinex module
Home-page: https://github.com/bopo/mooquant_bitfinex
Author: bopo.wang
Author-email: ibopo@126.com
License: MIT license
Keywords: mooquant_bitfinex
Platform: UNKNOWN
Classifier: Development Status :: 2 - Pre-Alpha
Classifier: Intended Audience :: Developers
Classifier: License :: OSI Approved :: MIT License
Classifier: Natural Language :: English
Classifier: Programming Language :: Python :: 3
Classifier: Programming Language :: Python :: 3.3
Classifier: Programming Language :: Python :: 3.4
Classifier: Programming Language :: Python :: 3.5
Classifier: Programming Language :: Python :: 3.6
Classifier: Programming Language :: Python :: 3.7
Requires-Dist: mooquant
